pyaudisam/__init__.py
pyaudisam/__main__.py
pyaudisam/analyser.py
pyaudisam/analysis.py
pyaudisam/data.py
pyaudisam/engine.py
pyaudisam/executor.py
pyaudisam/log.py
pyaudisam/main.py
pyaudisam/optanalyser.py
pyaudisam/optimisation.py
pyaudisam/optimiser.py
pyaudisam/report.py
pyaudisam/utils.py
pyaudisam/mcds/anlys.htpl
pyaudisam/mcds/fulltop.htpl
pyaudisam/mcds/pretop.htpl
pyaudisam/mcds/stat-mod-notes.txt
pyaudisam/mcds/stat-mod-specs.old.txt
pyaudisam/mcds/stat-mod-specs.txt
pyaudisam/mcds/stat-mod-trans.txt
pyaudisam/mcds/stat-row-specs.txt
pyaudisam/mcds/top.htpl
pyaudisam/report/fa-angle-up.svg
pyaudisam/report/fa-arrow-left-hover.svg
pyaudisam/report/fa-arrow-left.svg
pyaudisam/report/fa-arrow-right-hover.svg
pyaudisam/report/fa-arrow-right.svg
pyaudisam/report/fa-arrow-up-hover.svg
pyaudisam/report/fa-arrow-up.svg
pyaudisam/report/fa-feather-alt.svg
pyaudisam/report/fa-file-excel-hover.svg
pyaudisam/report/fa-file-excel.svg
pyaudisam/report/report.css
pyaudisam-1.2.0.dist-info/LICENSE.txt
pyaudisam-1.2.0.dist-info/METADATA
pyaudisam-1.2.0.dist-info/WHEEL
pyaudisam-1.2.0.dist-info/top_level.txt
pyaudisam-1.2.0.dist-info/RECORD
