Metadata-Version: 2.1
Name: pyaudisam
Version: 1.2.0
Summary: Distance Sampling automation through python and Distance software
Home-page: https://github.com/denmedius/pyaudisam
Author: denmedius
Author-email: fefeqe22.vucuqu82@murena.io
License: GPLv3+
Classifier: Topic :: Software Development :: Libraries
Classifier: Topic :: Software Development :: Libraries :: Python Modules
Classifier: Intended Audience :: Science/Research
Classifier: Development Status :: 3 - Alpha
Classifier: License :: OSI Approved :: GNU General Public License v3 or later (GPLv3+)
Classifier: Programming Language :: Python :: 3 :: Only
Classifier: Programming Language :: Python :: 3.9
Classifier: Environment :: Win32 (MS Windows)
Requires-Python: >=3.9
License-File: LICENSE.txt
Requires-Dist: numpy <1.27,>=1.22.4
Requires-Dist: pandas <2.3,>=2.1.0
Requires-Dist: openpyxl <3.2,>=3.0.10
Requires-Dist: xlrd ~=2.0
Requires-Dist: odfpy ~=1.4
Requires-Dist: matplotlib <3.9,>=3.1
Requires-Dist: jinja2 <3.2,>=3.1.2
Requires-Dist: zoopt ~=0.4
Requires-Dist: packaging
Provides-Extra: test
Requires-Dist: lxml >=5.0 ; extra == 'test'
Requires-Dist: pytest >=8.0 ; extra == 'test'
Requires-Dist: pytest-cov ; extra == 'test'
